README.rst
setup.py
wilddog/__init__.py
wilddog/async.py
wilddog/decorators.py
wilddog/jsonutil.py
wilddog/lazy.py
wilddog/wilddog.py
wilddog/wilddog_token_generator.py
wilddog_python.egg-info/PKG-INFO
wilddog_python.egg-info/SOURCES.txt
wilddog_python.egg-info/dependency_links.txt
wilddog_python.egg-info/not-zip-safe
wilddog_python.egg-info/requires.txt
wilddog_python.egg-info/top_level.txt