Metadata-Version: 1.1
Name: wilddog-python
Version: 1.0
Summary: Python interface to the Wilddog's REST API.
Home-page: http://github.com/WildDogTeam/wilddog-python
Author: Li Jiale
Author-email: lijiale@wilddog.com
License: MIT
Keywords: wilddog python
Platform: UNKNOWN
Classifier: Development Status :: 5 - Production/Stable
Classifier: Environment :: Console
Classifier: Intended Audience :: Developers
Classifier: License :: OSI Approved :: MIT License
Classifier: Operating System :: OS Independent
Classifier: Programming Language :: Python :: 2.6
Classifier: Programming Language :: Python :: 2.7
Classifier: Programming Language :: Python :: 3.2
Classifier: Natural Language :: English
